[
    {
        "nutrientId": 1,
        "amount": 0
    },
    {
        "nutrientId": 2,
        "amount": 0
    },
    {
        "nutrientId": 3,
        "amount": 0.8
    },
    {
        "nutrientId": 4,
        "amount": 0.33
    },
    {
        "nutrientId": 5,
        "amount": 0.09
    },
    {
        "nutrientId": 6,
        "amount": 0.8
    },
    {
        "nutrientId": 8,
        "amount": 46
    },
    {
        "nutrientId": 9,
        "amount": 0
    },
    {
        "nutrientId": 10,
        "amount": 0
    },
    {
        "nutrientId": 11,
        "amount": 47
    },
    {
        "nutrientId": 12,
        "amount": 471
    },
    {
        "nutrientId": 13,
        "amount": 414
    },
    {
        "nutrientId": 14,
        "amount": 142
    },
    {
        "nutrientId": 15,
        "amount": 4.7
    },
    {
        "nutrientId": 16,
        "amount": 3.6
    },
    {
        "nutrientId": 18,
        "amount": 20
    },
    {
        "nutrientId": 19,
        "amount": 12
    }
]